odoo/addons/web_timeline/README.rst
odoo/addons/web_timeline/__init__.py
odoo/addons/web_timeline/__manifest__.py
odoo/addons/web_timeline/i18n/es.po
odoo/addons/web_timeline/i18n/fr.po
odoo/addons/web_timeline/i18n/hr.po
odoo/addons/web_timeline/i18n/nl_NL.po
odoo/addons/web_timeline/i18n/web_timeline.pot
odoo/addons/web_timeline/models/__init__.py
odoo/addons/web_timeline/models/ir_view.py
odoo/addons/web_timeline/static/description/icon.png
odoo/addons/web_timeline/static/lib/vis/vis-timeline-graph2d.min.css
odoo/addons/web_timeline/static/lib/vis/vis-timeline-graph2d.min.js
odoo/addons/web_timeline/static/src/css/web_timeline.css
odoo/addons/web_timeline/static/src/js/timeline_canvas.js
odoo/addons/web_timeline/static/src/js/timeline_controller.js
odoo/addons/web_timeline/static/src/js/timeline_model.js
odoo/addons/web_timeline/static/src/js/timeline_renderer.js
odoo/addons/web_timeline/static/src/js/timeline_view.js
odoo/addons/web_timeline/static/src/xml/web_timeline.xml
odoo/addons/web_timeline/views/web_timeline.xml
odoo11_addon_web_timeline-11.0.1.4.3.dist-info/METADATA
odoo11_addon_web_timeline-11.0.1.4.3.dist-info/WHEEL
odoo11_addon_web_timeline-11.0.1.4.3.dist-info/top_level.txt
odoo11_addon_web_timeline-11.0.1.4.3.dist-info/RECORD
